[
  {
    "name":"Backlog",
    "items": [
      {
        "id":12323,
        "priority": 0,
        "title": "Поправить карточку товара на главной"
      },
      {
        "id":2,
        "priority": 2,
        "title": "Не работает модальное окно при нажатии на карточку"
      }
    ]
  },
  {
    "name":"In Progress",
    "items": [
      {
        "id":3,
        "priority": 1,
        "title": "Добавить в базу поле 'Чаты'"
      }
    ]
  },
  {
    "name":"На проверку",
    "items": [
      {
        "id":4,
        "priority": 2,
        "title": " Добавить метрику"
      },
      {
        "id":5,
        "priority": 0,
        "title": "Добавить социальные сети"
      }
    ]
  },
  {
    "name":"Done",
    "items": [
      {
        "id":6,
        "priority": 0,
        "title": "Убрать блок 'О нас'"
      },
      {
        "id":7,
        "priority": 1,
        "title": "Доработать карточку партнеров"
      },
      {
        "id":8,
        "priority": 2,
        "title": "Поменять размер шрифта"
      }
    ]
  }
]